lektor_amp.py
setup.py
lektor_amp.egg-info/PKG-INFO
lektor_amp.egg-info/SOURCES.txt
lektor_amp.egg-info/dependency_links.txt
lektor_amp.egg-info/entry_points.txt
lektor_amp.egg-info/top_level.txt