Metadata-Version: 1.0
Name: lektor-amp
Version: 0.1.1
Summary: Create an amp version of your website.
Home-page: https://github.com/rebeling/lektor-amp
Author: Matthias Rebel
Author-email: webmaster@rebeling.net
License: MIT
Platform: UNKNOWN
